pyxavi_activitypub/__init__.py
pyxavi_activitypub/firefish.py
pyxavi_activitypub/mastodon_helper.py
pyxavi_activitypub/mastodon_publisher.py
pyxavi_activitypub-0.1.0.dist-info/LICENSE
pyxavi_activitypub-0.1.0.dist-info/METADATA
pyxavi_activitypub-0.1.0.dist-info/WHEEL
pyxavi_activitypub-0.1.0.dist-info/RECORD
