Metadata-Version: 2.3
Name: pyxavi-activitypub
Version: 0.1.0
Summary: Set of utilities related to the Fediverse to assist on simple Python projects
License: GPLv3
Author: Xavier Arnaus
Author-email: xavi@arnaus.net
Requires-Python: >=3.9,<4.0
Classifier: License :: OSI Approved :: GNU General Public License v3 (GPLv3)
Classifier: License :: Other/Proprietary License
Classifier: Operating System :: OS Independent
Classifier: Programming Language :: Python :: 3
Classifier: Programming Language :: Python :: 3.9
Classifier: Programming Language :: Python :: 3.10
Classifier: Programming Language :: Python :: 3.11
Classifier: Programming Language :: Python :: 3.12
Classifier: Programming Language :: Python :: 3.13
Requires-Dist: Mastodon.py (==1.8.1)
Requires-Dist: pyxavi (>=1.0.0,<2.0.0)
Requires-Dist: requests (>=2.28.0,<3.0.0)
Project-URL: Homepage, https://github.com/XaviArnaus/pyxavi-activitypub
Project-URL: Repository, https://github.com/XaviArnaus/pyxavi-activitypub
